cmdbashinteractive/README.MD
cmdbashinteractive/__init__.py
cmdbashinteractive/requirements.txt
cmdbashinteractive/thirdparty.json
cmdbashinteractive-0.10.dist-info/LICENSE.rst
cmdbashinteractive-0.10.dist-info/METADATA
cmdbashinteractive-0.10.dist-info/WHEEL
cmdbashinteractive-0.10.dist-info/top_level.txt
cmdbashinteractive-0.10.dist-info/RECORD
