Metadata-Version: 2.1
Name: cmdbashinteractive
Version: 0.10
Summary: Interact with subprocesses running both bash.exe (CygWin) and cmd.exe without terminating them.
Home-page: https://github.com/hansalemaos/cmdbashinteractive
Author: Johannes Fischer
Author-email: aulasparticularesdealemaosp@gmail.com
License: MIT
Keywords: bash,cmd,cygwin
Classifier: Development Status :: 4 - Beta
Classifier: Programming Language :: Python :: 3 :: Only
Classifier: Programming Language :: Python :: 3.10
Classifier: Topic :: Software Development :: Libraries :: Python Modules
Classifier: Topic :: Utilities
License-File: LICENSE.rst
